hhonestjson/__init__.py
hhonestjson/main.py
hhonestjson-0.1.3.dist-info/METADATA
hhonestjson-0.1.3.dist-info/WHEEL
hhonestjson-0.1.3.dist-info/top_level.txt
hhonestjson-0.1.3.dist-info/RECORD
