Metadata-Version: 2.1
Name: hhonestjson
Version: 0.1.3
Summary: This package is made for typosquatting demo purposes only. While it does nothing harmful (it puts a text file on your machine), it is not recommended you install it, because it is useless.
